<?xml version="1.0" encoding="UTF-8"?>
<objects serializationModel="Studio.02.02.00">
	<object class="AudioFile" id="{f5b52a0a-a581-4c40-9063-5575a7be5b1f}">
		<property name="assetPath">
			<value>Music/Cute UI _ Interact Sound Effects Pack/AUDIO/Pop/Mouth/SFX_Pop_Mouth_High_2.wav</value>
		</property>
		<property name="frequencyInKHz">
			<value>44.0999985</value>
		</property>
		<property name="channelCount">
			<value>1</value>
		</property>
		<property name="length">
			<value>0.21877551020408162</value>
		</property>
		<relationship name="masterAssetFolder">
			<destination>{53a54653-aaae-4aa3-b222-14ad26770a97}</destination>
		</relationship>
	</object>
</objects>
